{
	"title": "Aplicación transaccional de Parranderos Uniandes",
	"frameH": 600,
	"frameW": 800,
	"bannerPath": "./src/main/resources/config/logo.png",
	"menuBar":
	[
		{ "menuTitle": "Registro",
		  "options":
			[
				
				{
					"label": "Login",
					"event": "login"
				},
				{
					"label": "Informacion usuario",
					"event": "infoUsuario"
				},
				{
					"label": "Logout",
					"event": "logout"
				}
			]
		},
		{ "menuTitle": "Modificacion",
		  "options":
			[
				{
					"label": "RF1 Registrar Operador",
					"event": "registrarOperador"
				},
				{
					"label": "RF2 Registrar Alojamiento",
					"event": "registrarAlojamiento"
				},
				{
					"label": "RF2 Registrar Oferta",
					"event": "registrarOferta"
				},
				{
					"label": "RF3 Registrar Cliente",
					"event": "registrarCliente"
				},
				
				{
					"label": "RF4 Registrar Reserva",
					"event": "registrarReserva"
				},
				{
					"label": "RF5 Cancelar Reserva",
					"event": "cancelarReserva"
				},
				{
					"label": "RF6 Retirar Alojamiento",
					"event": "retirarAlojamiento"
				},
				{
					"label": "RF7 Registrar Reserva Colectiva",
					"event": "registrarReservaColectiva"
				},
				{
					"label": "RF8 Cancelar Reserva Colectiva",
					"event": "cancelarReservaColectiva"
				},
				{
					"label": "RF9 Deshabilitar Oferta Alojamiento",
					"event": "deshabilitarAlojamiento"
				},
				{
					"label": "RF10 Habilitar Oferta Alojamiento",
					"event": "habilitarAlojamiento"
				}
			]
		},
		{ "menuTitle": "Consulta",
		  "options":
			[
				{
					"label": "RFC1 Dinero recibido por cada proveedor",
					"event": "dineroPorProveedor"
				},
				{
					"label": "RFC2 20 Ofertas mas populares",
					"event": "ofertasPopulares"
				},
				{
					"label": "RFC3 Indice de Ocupacion",
					"event": "indiceOcupacion"
				},
				{
					"label": "RFC4 Alojamientos por dotacion",
					"event": "alojamientosPorDotacion"
				},
				{
					"label": "RFC5 Uso de AlohAndes por tipo de Usuario",
					"event": "usoPorTipo"
				},
				{
					"label": "RFC6 Uso de AlohAndes por Usuario",
					"event": "usoPorUsuario"
				},
				{
					"label": "RFC7 Analizar Operación",
					"event": "analisisOperacion"
				},
				{
					"label": "RFC8 Clientes Frecuentes",
					"event": "clientesFrecuentes"
				},
				{
					"label": "RFC9 Ofertas con poca Demanda",
					"event": "ofertasPocaDemanda"
				},
				{
					"label": "RFC10 Consultar Consumo",
					"event": "consultarConsumo1"
				},
				{
					"label": "RFC11 Consultar Consumo v2",
					"event": "consultarConsumo2"
				},
				{
					"label": "RFC12 Consultar Funcionamiento",
					"event": "consultarFuncionamiento"
				},
				{
					"label": "RFC13 Consultar Buenos Clientes",
					"event": "consultarBuenosClientes"
				}
			]
		},
		{ "menuTitle": "Mantenimiento",
		  "options":
			[
				{
					"label": "Mostrar log AlohAndes",
					"event": "mostrarLogAlohAndes"
				},
				{
					"label": "Mostrar log datanuecleus",
					"event": "mostrarLogDatanuecleus"
				},
				{
					"label": "Limpiar log de AlohAndes",
					"event": "limpiarLogAlohAndes"
				},
				{
					"label": "Limpiar log de datanucleus",
					"event": "limpiarLogDatanucleus"
				},
				{
					"label": "Limpiar Base de Datos",
					"event": "limpiarBD"
				}
			]
		},		
		{ "menuTitle": "Documentación",
		  "options":
			[
				{
					"label": "Presentación general",
					"event": "mostrarPresentacionGeneral"
				},
				{
					"label": "Modelo conceptual",
					"event": "mostrarModeloConceptual"
				},
				{
					"label": "Esquema de la BD",
					"event": "mostrarEsquemaBD"
				},
				{
					"label": "Script creación de la BD",
					"event": "mostrarScriptBD"
				},
				{
					"label": "Arquitectura de referencia",
					"event": "mostrarArqRef"
				},
				{
					"label": "Javadoc AlohAndes",
					"event": "mostrarJavadoc"
				}
			]
		},		
		{ "menuTitle": "Acerca de ...",
		  "options":
			[
				{
					"label": "Acerca de ...",
					"event": "acercaDe"
				}
			]
		}		
		
	]
}
	